odoo/addons/stock_inventory_turnover_report/README.rst
odoo/addons/stock_inventory_turnover_report/__init__.py
odoo/addons/stock_inventory_turnover_report/__manifest__.py
odoo/addons/stock_inventory_turnover_report/i18n/it.po
odoo/addons/stock_inventory_turnover_report/i18n/stock_inventory_turnover_report.pot
odoo/addons/stock_inventory_turnover_report/models/__init__.py
odoo/addons/stock_inventory_turnover_report/models/product_product.py
odoo/addons/stock_inventory_turnover_report/readme/CONTRIBUTORS.rst
odoo/addons/stock_inventory_turnover_report/readme/DESCRIPTION.rst
odoo/addons/stock_inventory_turnover_report/readme/USAGE.rst
odoo/addons/stock_inventory_turnover_report/static/description/icon.png
odoo/addons/stock_inventory_turnover_report/static/description/index.html
odoo/addons/stock_inventory_turnover_report/views/product_views.xml
odoo12_addon_stock_inventory_turnover_report-12.0.1.0.1.dist-info/METADATA
odoo12_addon_stock_inventory_turnover_report-12.0.1.0.1.dist-info/WHEEL
odoo12_addon_stock_inventory_turnover_report-12.0.1.0.1.dist-info/top_level.txt
odoo12_addon_stock_inventory_turnover_report-12.0.1.0.1.dist-info/RECORD
